stacks_snippet/__init__.py
stacks_snippet/admin.py
stacks_snippet/apps.py
stacks_snippet/models.py
stacks_snippet/serializers.py
stacks_snippet/stuff.py
stacks_snippet/migrations/0001_initial.py
stacks_snippet/migrations/0002_snippet_display_title.py
stacks_snippet/migrations/__init__.py
stacks_snippet/templates/stacks_snippet/snippet-full_width.html
stacks_snippet-0.1.1.dist-info/DESCRIPTION.rst
stacks_snippet-0.1.1.dist-info/LICENSE.txt
stacks_snippet-0.1.1.dist-info/METADATA
stacks_snippet-0.1.1.dist-info/metadata.json
stacks_snippet-0.1.1.dist-info/RECORD
stacks_snippet-0.1.1.dist-info/top_level.txt
stacks_snippet-0.1.1.dist-info/WHEEL
